sap_cf_destination/__init__.py
sap_cf_destination/main.py
sap_cf_destination/py.typed
sap_cf_destination/core/__init__.py
sap_cf_destination/core/connectivity.py
sap_cf_destination/core/destination.py
sap_cf_destination/core/models.py
sap_cf_destination/core/settings.py
sap_cf_destination-0.1.2.dist-info/METADATA
sap_cf_destination-0.1.2.dist-info/WHEEL
sap_cf_destination-0.1.2.dist-info/licenses/LICENSE
sap_cf_destination-0.1.2.dist-info/RECORD
