Metadata-Version: 2.4
Name: sap-cf-destination
Version: 0.1.2
Summary: SAP Destination SDK for Cloud Foundry
Project-URL: Repository, https://github.com/karthikr029/sap-cf-destination.git
Project-URL: Issues, https://github.com/karthikr029/sap-cf-destination/issues
Author-email: Karthik Ravi <karthik.r029@gmail.com>
License-Expression: Apache-2.0
License-File: LICENSE
Classifier: Development Status :: 4 - Beta
Classifier: Intended Audience :: Developers
Classifier: Programming Language :: Python :: 3
Classifier: Programming Language :: Python :: 3.9
Classifier: Programming Language :: Python :: 3.10
Classifier: Programming Language :: Python :: 3.11
Classifier: Programming Language :: Python :: 3.13
Classifier: Topic :: Software Development :: Build Tools
Requires-Python: >=3.9
Requires-Dist: httpx>=0.28.1
Requires-Dist: pydantic-settings>=2.12.0
